siibra_cli/__init__.py
siibra_cli/cli.py
siibra_cli-0.1.dist-info/LICENSE
siibra_cli-0.1.dist-info/METADATA
siibra_cli-0.1.dist-info/WHEEL
siibra_cli-0.1.dist-info/entry_points.txt
siibra_cli-0.1.dist-info/top_level.txt
siibra_cli-0.1.dist-info/RECORD
