Metadata-Version: 2.1
Name: siibra-cli
Version: 0.1
Summary: Basic commandline client for siibra - a software toolsuite for interacting with brain atlases
Home-page: https://github.com/FZJ-INM1-BDA/siibra-cli
Author: Big Data Analytics Group, Forschungszentrum Juelich, Institute of Neuroscience and Medicine (INM-1)
Author-email: inm1-bda@fz-juelich.de
Classifier: Development Status :: 2 - Pre-Alpha
Classifier: Programming Language :: Python :: 3.7
Classifier: Programming Language :: Python :: 3.8
Classifier: Operating System :: OS Independent
Classifier: Intended Audience :: Developers
Requires-Python: >=3.7
License-File: LICENSE
Requires-Dist: siibra (>=0.3a16)
Requires-Dist: click (>=8.0)
Requires-Dist: click-plugins (>=1.0)
Requires-Dist: simple-term-menu (>=1.4)
